MANIFEST.in
requirements.txt
setup.py
api/__init__.py
api/__main__.py
api/authentication.py
api/components.py
api/conf.py
api/doc.py
api/endpoints.py
api/exceptions.py
api/icons.py
api/middleware.py
api/models.py
api/pagination.py
api/permissions.py
api/serializers.py
api/signals.py
api/specification.py
api/statistics.py
api/tasks.py
api/tests.py
api/threadlocals.py
api/urls.py
api/utils.py
api/viewsets.py
api/cloud/__init__.py
api/cloud/printer.py
api/cloud/server.py
api/management/__init__.py
api/management/commands/__init__.py
api/management/commands/cloud.py
api/management/commands/reset_passwords.py
api/management/commands/selenium.py
api/management/commands/startserver.py
api/management/commands/sync.py
api/management/commands/sync_roles.py
api/management/commands/test.py
api/migrations/0001_initial.py
api/migrations/0002_scope_active.py
api/migrations/0003_alter_scope_active_alter_scope_modelname_and_more.py
api/migrations/0004_role_delete_scope.py
api/migrations/__init__.py
api/static/app/index.html
api/static/app/assets/index-56fd4751.js
api/static/app/css/core.css
api/static/app/css/fontawesome.min.css
api/static/app/css/solid.min.css
api/static/app/css/fonts/rawline-400.woff
api/static/app/css/fonts/rawline-400i.woff
api/static/app/js/autocomplete.js
api/static/app/js/core.js
api/static/app/js/echarts.min.js
api/static/app/js/jquery-3.6.0.min.js
api/static/app/js/qrcode.min.js
api/static/app/js/settings.js
api/static/app/js/vanilla-masker.min.js
api/static/app/webfonts/fa-solid-900.ttf
api/static/app/webfonts/fa-solid-900.woff2
api/test/__init__.py
api/test/selenium/__init__.py
api/test/selenium/browser.py
yml_api.egg-info/PKG-INFO
yml_api.egg-info/SOURCES.txt
yml_api.egg-info/dependency_links.txt
yml_api.egg-info/requires.txt
yml_api.egg-info/top_level.txt