Metadata-Version: 2.1
Name: yml-api
Version: 0.0.5
Summary: API generator based on yml file
Home-page: https://github.com/brenokcc
Author: Breno Silva
Author-email: brenokcc@yahoo.com.br
License: BSD License
Classifier: Environment :: Web Environment
Classifier: Framework :: Django
Classifier: Intended Audience :: Developers
Classifier: License :: OSI Approved :: BSD License
Classifier: Operating System :: OS Independent
Classifier: Programming Language :: Python
Classifier: Topic :: Internet :: WWW/HTTP
Classifier: Topic :: Internet :: WWW/HTTP :: Dynamic Content
Provides-Extra: dev
